plott_langgraph/__init__.py
plott_langgraph/event_translator.py
plott_langgraph/graph_proxy.py
plott_langgraph/py.typed
plott_langgraph/types.py
plott_langgraph/utils.py
plott_sdk_langgraph-0.0.1a1.dist-info/METADATA
plott_sdk_langgraph-0.0.1a1.dist-info/WHEEL
plott_sdk_langgraph-0.0.1a1.dist-info/RECORD
