Metadata-Version: 2.4
Name: plott-sdk-langgraph
Version: 0.0.1a1
Summary: Plott Analytics SDK for LangGraph - Automatic analytics tracking for LangGraph
Project-URL: Homepage, https://plott.ai
Project-URL: Documentation, https://docs.plott.ai/sdk/langgraph
Author-email: Plott Analytics <hello@plott.ai>
License-Expression: Apache-2.0
Keywords: agents,ai,analytics,langchain,langgraph,llm,plott
Classifier: Development Status :: 4 - Beta
Classifier: Intended Audience :: Developers
Classifier: License :: OSI Approved :: MIT License
Classifier: Programming Language :: Python :: 3
Classifier: Programming Language :: Python :: 3.9
Classifier: Programming Language :: Python :: 3.10
Classifier: Programming Language :: Python :: 3.11
Classifier: Programming Language :: Python :: 3.12
Classifier: Topic :: Software Development :: Libraries :: Python Modules
Classifier: Typing :: Typed
Requires-Python: >=3.9
Requires-Dist: langchain-core>=0.2.0
Requires-Dist: langgraph>=0.2.0
Requires-Dist: plott-sdk-core>=0.0.1a0
Provides-Extra: dev
Requires-Dist: langchain-openai>=0.1.0; extra == 'dev'
Requires-Dist: mypy>=1.0.0; extra == 'dev'
Requires-Dist: pytest-asyncio>=0.21.0; extra == 'dev'
Requires-Dist: pytest-cov>=4.0.0; extra == 'dev'
Requires-Dist: pytest>=7.0.0; extra == 'dev'
Requires-Dist: ruff>=0.1.0; extra == 'dev'
